README.rst
setup.py
salsa/__init__.py
salsa/salsa.py
salsa/testing.py
salsa/time.py
salsa.egg-info/PKG-INFO
salsa.egg-info/SOURCES.txt
salsa.egg-info/dependency_links.txt
salsa.egg-info/requires.txt
salsa.egg-info/top_level.txt